graphtransliterator/__init__.py
graphtransliterator/ambiguity.py
graphtransliterator/cli.py
graphtransliterator/compression.py
graphtransliterator/core.py
graphtransliterator/exceptions.py
graphtransliterator/graphs.py
graphtransliterator/initialize.py
graphtransliterator/process.py
graphtransliterator/rules.py
graphtransliterator/schemas.py
graphtransliterator/transliterators/README.rst
graphtransliterator/transliterators/__init__.py
graphtransliterator/transliterators/bundled.py
graphtransliterator/transliterators/example/__init__.py
graphtransliterator/transliterators/example/example.json
graphtransliterator/transliterators/example/example.yaml
graphtransliterator/transliterators/example/tests/example_tests.yaml
graphtransliterator/transliterators/example/tests/test_example.py
graphtransliterator/transliterators/itrans_devanagari_to_unicode/__init__.py
graphtransliterator/transliterators/itrans_devanagari_to_unicode/itrans_devanagari_to_unicode.json
graphtransliterator/transliterators/itrans_devanagari_to_unicode/itrans_devanagari_to_unicode.yaml
graphtransliterator/transliterators/itrans_devanagari_to_unicode/tests/itrans_devanagari_to_unicode_tests.yaml
graphtransliterator/transliterators/schemas.py
graphtransliterator-1.2.4.dist-info/LICENSE
graphtransliterator-1.2.4.dist-info/METADATA
graphtransliterator-1.2.4.dist-info/WHEEL
graphtransliterator-1.2.4.dist-info/RECORD
