Metadata-Version: 2.1
Name: graphtransliterator
Version: 1.2.4
Summary: A graph-based transliteration tool
Home-page: https://github.com/seanpue/graphtransliterator
License: MIT
Author: A. Sean Pue
Author-email: seanpue@users.noreply.github.com
Requires-Python: >=3.9,<4.0
Classifier: License :: OSI Approved :: MIT License
Classifier: Programming Language :: Python :: 3
Classifier: Programming Language :: Python :: 3.9
Classifier: Programming Language :: Python :: 3.10
Classifier: Programming Language :: Python :: 3.11
Requires-Dist: PyYAML (>=6.0.1,<7.0.0)
Requires-Dist: click (>=8.1.7,<9.0.0)
Requires-Dist: marshmallow (>=3.20.1,<4.0.0)
Project-URL: Documentation, https://graphtransliterator.readthedocs.org
Project-URL: Repository, https://github.com/seanpue/graphtransliterator
